topsis_rishika/__init__.py
topsis_rishika/main.py
topsis_rishika_102313050-1.0.0.dist-info/licenses/LICENSE
topsis_rishika_102313050-1.0.0.dist-info/METADATA
topsis_rishika_102313050-1.0.0.dist-info/WHEEL
topsis_rishika_102313050-1.0.0.dist-info/entry_points.txt
topsis_rishika_102313050-1.0.0.dist-info/top_level.txt
topsis_rishika_102313050-1.0.0.dist-info/RECORD
